ArtificialInteligenceLeonardoAraujoDosSantos/README.md
ArtificialInteligenceLeonardoAraujoDosSantos/__init__.py
ArtificialInteligenceLeonardoAraujoDosSantos/__main__.py
ArtificialInteligenceLeonardoAraujoDosSantos/file.epub
ArtificialInteligenceLeonardoAraujoDosSantos/index.html
ArtificialInteligenceLeonardoAraujoDosSantos/css/__init__.py
ArtificialInteligenceLeonardoAraujoDosSantos/css/annotations.css
ArtificialInteligenceLeonardoAraujoDosSantos/css/main.css
ArtificialInteligenceLeonardoAraujoDosSantos/css/normalize.css
ArtificialInteligenceLeonardoAraujoDosSantos/css/popup.css
ArtificialInteligenceLeonardoAraujoDosSantos/font/__init__.py
ArtificialInteligenceLeonardoAraujoDosSantos/font/fontello.eot
ArtificialInteligenceLeonardoAraujoDosSantos/font/fontello.svg
ArtificialInteligenceLeonardoAraujoDosSantos/font/fontello.ttf
ArtificialInteligenceLeonardoAraujoDosSantos/font/fontello.woff
ArtificialInteligenceLeonardoAraujoDosSantos/img/__init__.py
ArtificialInteligenceLeonardoAraujoDosSantos/img/annotator-glyph-sprite.png
ArtificialInteligenceLeonardoAraujoDosSantos/img/annotator-icon-sprite.png
ArtificialInteligenceLeonardoAraujoDosSantos/img/apple-touch-icon.png
ArtificialInteligenceLeonardoAraujoDosSantos/img/cancelfullscreen.png
ArtificialInteligenceLeonardoAraujoDosSantos/img/close.png
ArtificialInteligenceLeonardoAraujoDosSantos/img/fullscreen.png
ArtificialInteligenceLeonardoAraujoDosSantos/img/loader.gif
ArtificialInteligenceLeonardoAraujoDosSantos/img/menu-icon.png
ArtificialInteligenceLeonardoAraujoDosSantos/img/save.png
ArtificialInteligenceLeonardoAraujoDosSantos/img/saved.png
ArtificialInteligenceLeonardoAraujoDosSantos/img/settings-s.png
ArtificialInteligenceLeonardoAraujoDosSantos/img/settings.png
ArtificialInteligenceLeonardoAraujoDosSantos/img/star.png
ArtificialInteligenceLeonardoAraujoDosSantos/js/__init__.py
ArtificialInteligenceLeonardoAraujoDosSantos/js/epub.js
ArtificialInteligenceLeonardoAraujoDosSantos/js/epub.min.js
artificial_inteligence_leonardo_araujo_dos_santos-2024.3.3.0.dist-info/METADATA
artificial_inteligence_leonardo_araujo_dos_santos-2024.3.3.0.dist-info/WHEEL
artificial_inteligence_leonardo_araujo_dos_santos-2024.3.3.0.dist-info/entry_points.txt
artificial_inteligence_leonardo_araujo_dos_santos-2024.3.3.0.dist-info/top_level.txt
artificial_inteligence_leonardo_araujo_dos_santos-2024.3.3.0.dist-info/RECORD
